LICENSE
MANIFEST.in
README.rst
setup.py
Gunstar.egg-info/PKG-INFO
Gunstar.egg-info/SOURCES.txt
Gunstar.egg-info/dependency_links.txt
Gunstar.egg-info/not-zip-safe
Gunstar.egg-info/requires.txt
Gunstar.egg-info/top_level.txt
docs/application.rst
docs/configuration.rst
docs/handlers.rst
docs/index.rst
docs/installation.rst
docs/quickstart.rst
docs/routing.rst
docs/session.rst
docs/signals.rst
docs/testing.rst
gunstar/__init__.py
gunstar/app.py
gunstar/config.py
gunstar/http.py
gunstar/routing.py
gunstar/session.py
gunstar/signals.py
gunstar/template.py
gunstar/testing.py
gunstar/utils.py
gunstar.egg-info/SOURCES.txt
gunstar/templates/404.html
gunstar/templates/500.html
gunstar/templates/base_gunstar.html